pinterest/__init__.py
pinterest/__version__.py
pinterest/board.py
pinterest/config.py
pinterest/err.py
pinterest/me.py
pinterest/oauth2.py
pinterest/pin.py
pinterest/section.py
pinterest/user.py
pinterest/util.py
pinterest_api-0.0.8.dist-info/METADATA
pinterest_api-0.0.8.dist-info/RECORD
pinterest_api-0.0.8.dist-info/WHEEL
pinterest_api-0.0.8.dist-info/top_level.txt
