Metadata-Version: 2.1
Name: pinterest-api
Version: 0.0.8
Summary: Pinterest API client
Home-page: https://github.com/bryand1/python-pinterest-api
Author: Bryan Andrade
Author-email: me@bryanandrade.com
License: MIT
Platform: UNKNOWN
Classifier: Development Status :: 4 - Beta
Classifier: License :: OSI Approved :: MIT License
Classifier: Intended Audience :: Developers
Classifier: Natural Language :: English
Classifier: Programming Language :: Python
Classifier: Programming Language :: Python :: 3
Classifier: Programming Language :: Python :: 3.6
Classifier: Programming Language :: Python :: 3.7
Classifier: Programming Language :: Python :: Implementation :: CPython
Requires-Python: >=3.6.0
Requires-Dist: requests
